mac_tdavec/__init__.py
mac_tdavec/tdavec_core.c
mac_tdavec/tdavec_core.cpython-311-darwin.so
mac_tdavec/tdavec_core.pyx
mac_tdavec/unit_test.py
mac_tdavec/vectorizer.py
mac_tdavec-0.9.1.dist-info/licenses/LICENSE.txt
mac_tdavec-0.9.1.dist-info/METADATA
mac_tdavec-0.9.1.dist-info/WHEEL
mac_tdavec-0.9.1.dist-info/top_level.txt
mac_tdavec-0.9.1.dist-info/RECORD
