Metadata-Version: 2.4
Name: mac_tdavec
Version: 0.9.1
Requires-Python: >=3.11
License-File: LICENSE.txt
Requires-Dist: numpy
Requires-Dist: ripser
Dynamic: license-file
